rundevserver/__init__.py
rundevserver/apps.py
rundevserver/tests.py
rundevserver/management/__init__.py
rundevserver/management/commands/__init__.py
rundevserver/management/commands/rundevserver.py
django_rundevserver-0.3.1.dist-info/LICENSE.txt
django_rundevserver-0.3.1.dist-info/METADATA
django_rundevserver-0.3.1.dist-info/WHEEL
django_rundevserver-0.3.1.dist-info/top_level.txt
django_rundevserver-0.3.1.dist-info/RECORD
